qdarktheme/__init__.py
qdarktheme/main.py
qdarktheme/qtpy/QtCore/__init__.py
qdarktheme/qtpy/QtGui/__init__.py
qdarktheme/qtpy/QtSvg/__init__.py
qdarktheme/qtpy/QtWidgets/__init__.py
qdarktheme/qtpy/__init__.py
qdarktheme/qtpy/qt_compat.py
qdarktheme/qtpy/qt_version.py
qdarktheme/themes/__init__.py
qdarktheme/themes/dark/__init__.py
qdarktheme/themes/dark/palette.py
qdarktheme/themes/dark/stylesheet.py
qdarktheme/themes/dark/svg.py
qdarktheme/themes/light/__init__.py
qdarktheme/themes/light/palette.py
qdarktheme/themes/light/stylesheet.py
qdarktheme/themes/light/svg.py
qdarktheme/util.py
qdarktheme/widget_gallery/__init__.py
qdarktheme/widget_gallery/__main__.py
qdarktheme/widget_gallery/mainwindow.py
qdarktheme/widget_gallery/svg/announcement_24dp.svg
qdarktheme/widget_gallery/svg/circle_24dp.svg
qdarktheme/widget_gallery/svg/clear_24dp.svg
qdarktheme/widget_gallery/svg/contrast_24dp.svg
qdarktheme/widget_gallery/svg/crop_din_24dp.svg
qdarktheme/widget_gallery/svg/favorite_border_24dp.svg
qdarktheme/widget_gallery/svg/flip_to_front_24dp.svg
qdarktheme/widget_gallery/svg/folder_open_24dp.svg
qdarktheme/widget_gallery/svg/font_download_24dp.svg
qdarktheme/widget_gallery/svg/palette_24dp.svg
qdarktheme/widget_gallery/svg/settings_24dp.svg
qdarktheme/widget_gallery/svg/widgets_24dp.svg
qdarktheme/widget_gallery/ui/__init__.py
qdarktheme/widget_gallery/ui/dock_ui.py
qdarktheme/widget_gallery/ui/frame_ui.py
qdarktheme/widget_gallery/ui/widgets_ui.py
omnipose_theme-1.1.3.dist-info/LICENSE.txt
omnipose_theme-1.1.3.dist-info/METADATA
omnipose_theme-1.1.3.dist-info/WHEEL
omnipose_theme-1.1.3.dist-info/RECORD
