Metadata-Version: 2.1
Name: omnipose-theme
Version: 1.1.3
Summary: True gray variant of pyqtdarktheme for the Omnipose GUI.
Home-page: https://github.com/kevinjohncutler/omnipose-theme
License: MIT
Keywords: qt,stylesheets,dark-theme
Author: Yunosuke Ohsugi
Author-email: 63651161+5yutan5@users.noreply.github.com
Requires-Python: >=3.7
Classifier: Environment :: X11 Applications :: Qt
Classifier: License :: OSI Approved :: MIT License
Classifier: Natural Language :: English
Classifier: Operating System :: OS Independent
Classifier: Programming Language :: Python
Classifier: Programming Language :: Python :: 3
Classifier: Programming Language :: Python :: 3.7
Classifier: Programming Language :: Python :: 3.8
Classifier: Programming Language :: Python :: 3.9
Classifier: Programming Language :: Python :: 3.10
Classifier: Programming Language :: Python :: 3.11
Classifier: Programming Language :: Python :: 3.12
Classifier: Topic :: Software Development :: Libraries :: Python Modules
Provides-Extra: docs
Requires-Dist: pydata-sphinx-theme (>=0.7.2,<0.9.0) ; extra == "docs"
Requires-Dist: sphinx-panels (>=0.6.0,<0.7.0) ; extra == "docs"
Project-URL: Documentation, https://pyqtdarktheme.readthedocs.io
Project-URL: Repository, https://github.com/kevinjohncutler/omnipose-theme
